sentinel/__init__.py
sentinel/_version.py
sentinel/py.typed
sentinel/_internal/__init__.py
sentinel/v1/__init__.py
sentinel/v1/dto.py
sentinel/v1/models/__init__.py
sentinel/v1/models/block.py
sentinel/v1/models/subnet.py
sentinel/v1/providers/__init__.py
sentinel/v1/providers/base.py
sentinel/v1/providers/bittensor.py
sentinel/v1/services/__init__.py
sentinel/v1/services/sentinel.py
sentinel/v1/services/extractors/__init__.py
sentinel/v1/services/extractors/dividends.py
sentinel/v1/services/extractors/hyperparam.py
sentinel/v1/services/extractors/events/__init__.py
sentinel/v1/services/extractors/events/extractor.py
sentinel/v1/services/extractors/events/filters.py
sentinel/v1/services/extractors/extrinsics/__init__.py
sentinel/v1/services/extractors/extrinsics/extractor.py
sentinel/v1/services/extractors/extrinsics/filters.py
sentinel/v1/services/extractors/metagraph/__init__.py
sentinel/v1/services/extractors/metagraph/dto.py
sentinel/v1/services/extractors/metagraph/extractor.py
sentinel/v1/services/extractors/metagraph/filter.py
sentinel/v1/services/extractors/subnet/__init__.py
sentinel/v1/services/extractors/subnet/extractor.py
sentinel_cli/__init__.py
sentinel_cli/__main__.py
sentinel_cli/blocks.py
sentinel_cli/main.py
sentinel_cli/output.py
sentinel_cli/settings.py
sentinel_cli/commands/__init__.py
sentinel_cli/commands/block.py
sentinel_cli/commands/events.py
sentinel_cli/commands/extrinsics.py
sentinel_cli/commands/runtime.py
sentinel_cli/commands/subnet.py
bittensor_sentinel-0.1.4.dist-info/METADATA
bittensor_sentinel-0.1.4.dist-info/WHEEL
bittensor_sentinel-0.1.4.dist-info/entry_points.txt
bittensor_sentinel-0.1.4.dist-info/RECORD
