Metadata-Version: 2.4
Name: bittensor-sentinel
Version: 0.1.4
Project-URL: Source, https://github.com/bittensor-church/sentinel
Project-URL: Issue Tracker, https://github.com/bittensor-church/sentinel/issues
Author-email: Reef Technologies <opensource@reef.pl>
License: MIT
Classifier: Intended Audience :: Developers
Classifier: License :: OSI Approved :: MIT License
Classifier: Programming Language :: Python :: 3
Classifier: Programming Language :: Python :: 3.11
Classifier: Programming Language :: Python :: 3.12
Classifier: Topic :: Software Development :: Libraries
Requires-Python: >=3.11
Requires-Dist: asgiref>=3.11.0
Requires-Dist: bittensor>=10.0.0
Requires-Dist: pydantic>=2.12.5
Requires-Dist: structlog>=25.5.0
Requires-Dist: typer>=0.12.0
